QianduanXiaokeDiyiErqi/README.md
QianduanXiaokeDiyiErqi/__init__.py
QianduanXiaokeDiyiErqi/__main__.py
QianduanXiaokeDiyiErqi/file.epub
QianduanXiaokeDiyiErqi/index.html
QianduanXiaokeDiyiErqi/css/__init__.py
QianduanXiaokeDiyiErqi/css/annotations.css
QianduanXiaokeDiyiErqi/css/main.css
QianduanXiaokeDiyiErqi/css/normalize.css
QianduanXiaokeDiyiErqi/css/popup.css
QianduanXiaokeDiyiErqi/font/__init__.py
QianduanXiaokeDiyiErqi/font/fontello.eot
QianduanXiaokeDiyiErqi/font/fontello.svg
QianduanXiaokeDiyiErqi/font/fontello.ttf
QianduanXiaokeDiyiErqi/font/fontello.woff
QianduanXiaokeDiyiErqi/img/__init__.py
QianduanXiaokeDiyiErqi/img/annotator-glyph-sprite.png
QianduanXiaokeDiyiErqi/img/annotator-icon-sprite.png
QianduanXiaokeDiyiErqi/img/apple-touch-icon.png
QianduanXiaokeDiyiErqi/img/cancelfullscreen.png
QianduanXiaokeDiyiErqi/img/close.png
QianduanXiaokeDiyiErqi/img/fullscreen.png
QianduanXiaokeDiyiErqi/img/loader.gif
QianduanXiaokeDiyiErqi/img/menu-icon.png
QianduanXiaokeDiyiErqi/img/save.png
QianduanXiaokeDiyiErqi/img/saved.png
QianduanXiaokeDiyiErqi/img/settings-s.png
QianduanXiaokeDiyiErqi/img/settings.png
QianduanXiaokeDiyiErqi/img/star.png
QianduanXiaokeDiyiErqi/js/__init__.py
QianduanXiaokeDiyiErqi/js/epub.js
QianduanXiaokeDiyiErqi/js/epub.min.js
QianduanXiaokeDiyiErqi/js/epub.min.map
QianduanXiaokeDiyiErqi/js/hooks.min.js
QianduanXiaokeDiyiErqi/js/hooks.min.map
QianduanXiaokeDiyiErqi/js/reader.js
QianduanXiaokeDiyiErqi/js/reader.js.map
QianduanXiaokeDiyiErqi/js/reader.min.js
QianduanXiaokeDiyiErqi/js/reader.min.map
QianduanXiaokeDiyiErqi/js/hooks/__init__.py
QianduanXiaokeDiyiErqi/js/hooks/extensions/__init__.py
QianduanXiaokeDiyiErqi/js/hooks/extensions/highlight.js
QianduanXiaokeDiyiErqi/js/libs/__init__.py
QianduanXiaokeDiyiErqi/js/libs/jquery.min.js
QianduanXiaokeDiyiErqi/js/libs/localforage.min.js
QianduanXiaokeDiyiErqi/js/libs/screenfull.js
QianduanXiaokeDiyiErqi/js/libs/screenfull.min.js
QianduanXiaokeDiyiErqi/js/libs/zip.min.js
qianduan_xiaoke_diyi_erqi-2024.3.5.0.dist-info/METADATA
qianduan_xiaoke_diyi_erqi-2024.3.5.0.dist-info/WHEEL
qianduan_xiaoke_diyi_erqi-2024.3.5.0.dist-info/entry_points.txt
qianduan_xiaoke_diyi_erqi-2024.3.5.0.dist-info/top_level.txt
qianduan_xiaoke_diyi_erqi-2024.3.5.0.dist-info/RECORD
